pymetadata/__init__.py
pymetadata/cache.py
pymetadata/chebi.py
pymetadata/console.py
pymetadata/log.py
pymetadata/omex.py
pymetadata/omex_v2.py
pymetadata/py.typed
pymetadata/unichem.py
pymetadata/core/__init__.py
pymetadata/core/annotation.py
pymetadata/core/creator.py
pymetadata/core/synonym.py
pymetadata/core/xref.py
pymetadata/examples/__init__.py
pymetadata/examples/cache_path_example.py
pymetadata/examples/omex_example.py
pymetadata/examples/test.omex
pymetadata/examples/results/test_from_files.omex
pymetadata/examples/results/test_from_omex.omex
pymetadata/examples/results/testomex/README.md
pymetadata/examples/results/testomex/manifest.xml
pymetadata/examples/results/testomex/models/omex_comp.xml
pymetadata/examples/results/testomex/models/omex_comp_flat.xml
pymetadata/examples/results/testomex/models/omex_minimal.xml
pymetadata/identifiers/__init__.py
pymetadata/identifiers/miriam.py
pymetadata/identifiers/registry.py
pymetadata/metadata/__init__.py
pymetadata/metadata/eco.py
pymetadata/metadata/kisao.py
pymetadata/metadata/sbo.py
pymetadata/ontologies/__init__.py
pymetadata/ontologies/ols.py
pymetadata/ontologies/ontology.py
pymetadata/resources/ontologies/README.md
pymetadata/resources/templates/ontology_enum.pytemplate
pymetadata-0.5.10.dist-info/METADATA
pymetadata-0.5.10.dist-info/WHEEL
pymetadata-0.5.10.dist-info/licenses/LICENSE
pymetadata-0.5.10.dist-info/RECORD
