Metadata-Version: 2.4
Name: pymetadata
Version: 0.5.10
Summary: pymetadata are python utilities for working with metadata.
Author-email: Matthias König <konigmatt@googlemail.com>
Maintainer-email: Matthias König <konigmatt@googlemail.com>
License-File: LICENSE
Keywords: COMBINE,annotation,archive,metadata,modeling,standardization
Classifier: Development Status :: 4 - Beta
Classifier: Intended Audience :: Science/Research
Classifier: License :: OSI Approved :: MIT License
Classifier: Operating System :: OS Independent
Classifier: Programming Language :: Python :: 3.10
Classifier: Programming Language :: Python :: 3.11
Classifier: Programming Language :: Python :: 3.12
Classifier: Programming Language :: Python :: 3.13
Classifier: Programming Language :: Python :: 3.14
Classifier: Programming Language :: Python :: Implementation :: CPython
Classifier: Topic :: Scientific/Engineering
Classifier: Topic :: Scientific/Engineering :: Bio-Informatics
Requires-Python: >=3.10
Requires-Dist: depinfo>=2.2.0
Requires-Dist: fastobo>=0.14.1
Requires-Dist: jinja2>=3.1.6
Requires-Dist: lxml>=6.0.2
Requires-Dist: pronto>=2.7.2
Requires-Dist: pydantic>=2.12.5
Requires-Dist: requests>=2.32.5
Requires-Dist: rich>=14.2.0
Requires-Dist: xmltodict>=1.0.2
Provides-Extra: dev
Requires-Dist: bump-my-version>=1.2.6; extra == 'dev'
Requires-Dist: mypy>=1.19.1; extra == 'dev'
Requires-Dist: pre-commit>=4.5.1; extra == 'dev'
Requires-Dist: pytest-cov>=7.0.0; extra == 'dev'
Requires-Dist: pytest>=9.0.2; extra == 'dev'
Requires-Dist: ruff>=0.14.11; extra == 'dev'
Requires-Dist: tox>=4.34.1; extra == 'dev'
